README.txt
setup.py
candy/__init__.py
candy.candy.egg-info/PKG-INFO
candy.candy.egg-info/SOURCES.txt
candy.candy.egg-info/dependency_links.txt
candy.candy.egg-info/entry_points.txt
candy.candy.egg-info/namespace_packages.txt
candy.candy.egg-info/not-zip-safe
candy.candy.egg-info/paster_plugins.txt
candy.candy.egg-info/requires.txt
candy.candy.egg-info/top_level.txt
candy/candy/__init__.py
docs/HISTORY.txt