Metadata-Version: 1.0
Name: candy.candy
Version: 0.1.0
Summary: Grabs videos from youtube
Home-page: http://candy-candy.googlecode.com/
Author: Massimo Azzolini
Author-email: massimo.azzolini@gmail.com
License: GPL
Keywords: youtube candycandy pwnyoutube
Platform: UNKNOWN
Classifier: Programming Language :: Python
Classifier: Topic :: Software Development :: Libraries :: Python Modules
